Metadata-Version: 1.0
Name: commondist
Version: 0.2
Summary: Common distributions
Home-page: UNKNOWN
Author: Jason Ho
Author-email: jasonho0810@gmail.com
License: UNKNOWN
Platform: UNKNOWN
